{"singlePage": [], "startSite": "", "filingNum": "", "onePageListNum": 15, "commentLabelColor": "#006b75", "yearColorList": ["#bc4c00", "#0969da", "#1f883d", "#A333D0"], "i18n": "CN", "themeMode": "manual", "dayTheme": "light", "nightTheme": "dark", "urlMode": "pinyin", "script": "", "style": "", "head": "", "indexScript": "", "indexStyle": "", "bottomText": "", "showPostSource": 1, "iconList": {}, "UTC": 8, "rssSplit": "sentence", "exlink": {}, "needComment": 1, "allHead": "", "title": "\u786c\u6838\u6c34\u58a8", "subTitle": "3\u5e74\u521b\u59cb\u4ebaIP\u6444\u5f71\u5e08 INTJ \u5c04\u624b\u5ea7 \u5206\u4eab\u4e2a\u4eba\u6210\u957f\u3001\u9879\u76ee\u5b9e\u6218\u8d5a\u94b1\u65e5\u8bb0\u3001\u5929\u8d4b\u4f18\u52bf\u3001\u6d77\u5916\u9879\u76ee\u4fe1\u606f\u5dee\u3001 \u5065\u8eabing", "avatarUrl": "https://github.githubassets.com/favicons/favicon.svg", "GMEEK_VERSION": "last", "postListJson": {"P1": {"htmlDir": "docs/post/di-yi-pian-wen-zhang.html", "labels": ["documentation"], "postTitle": "\u7b2c\u4e00\u7bc7\u6587\u7ae0", "postUrl": "post/di-yi-pian-wen-zhang.html", "postSourceUrl": "https://github.com/hacksmo/hacksmo.github.io/issues/1", "commentNum": 0, "wordCount": 476, "description": "\u300a\u6211\u662f\u8c01\uff1f\u4e3a\u4ec0\u4e48\u6211\u4f1a\u4ece\u6df1\u5733\u6765\u5230\u5357\u4eac\u300b\r\n\r\n\u6211\u4e3a\u4ec0\u4e48\u9009\u62e9\u7edd\u5bf9\u7537\u4eba\r\n\r\n\u867d\u7136\u6211\u7ed9\u81ea\u5df1\u7684\u5b9a\u4e49\u662f\u6444\u5f71\u5e08\uff0c\u4f46\u6211\u5728\u6df1\u5733\u7684\u7b2c\u4e00\u4efd\u521b\u4e1a\u7ecf\u5386\u5c31\u662f\u505a\u521b\u59cb\u4eba ip \u6253\u9020\uff0c\uff08\u6652\u51fa\u5f53\u65f6\u7684\u5408\u5f71\u548c\u7167\u7247\uff09\u548c\u4e94\u767e\u4e07\u81ea\u5a92\u4f53\u7c89\u4e1d\u5927 v \u4e00\u8d77\u521b\u4e1a\uff0c\u975e\u5e38\u719f\u6089\u8001\u677f IP \u7684\u843d\u5730\u8fc7\u7a0b\r\n\r\n\u7edd\u5bf9\u7537\u4eba\u7684\u89c6\u9891\u62cd\u6444\u526a\u8f91\u90fd\u662f\u6211\u526a\u7684\uff0c\u90e8\u5206\u8fd0\u8425\u548c\u6587\u6848\u7b56\u5212\u5185\u5bb9\u4e5f\u6709\u6211\u6765\u505a\r\n\r\n\u300a\u7edd\u5bf9\u7537\u4eba\u80cc\u540e\u7684\u6444\u5f71\u5e08\u300b\r\n\r\n\u53ef\u4ee5\u662f\u4f5c\u8005\uff0c\u4e5f\u53ef\u4ee5\u662f\u7b14\u540d\r\n\r\n\u89c2\u5bdf\u8363\u8000\u7684\u4e0b\u8f7d\u5e02\u573a\uff0c\u770b\u8d44\u8baf\u7c7b\u4e0b\u8f7d\u6392\u540d\u90fd\u662f\u4ec0\u4e48\u8f6f\u4ef6\uff0c\u53bb\u66f4\u65b0\u8fd9\u4e9b\u5e73\u53f0\u7684\u5185\u5bb9\uff0c\u4eca\u65e5\u5934\u6761\uff0c\u767e\u5bb6\u53f7\uff0c\u6296\u97f3\uff0c\u5c0f\u7ea2\u4e66\uff0c\u516c\u4f17\u53f7\u7b49\u7b49\r\n\r\n\u53bb\u975e\u5e38\u5927\u6279\u91cf\u7684\u5199\u81ea\u5df1\u662f\u8c01\uff0c\u81ea\u5df1\u4e3a\u4ec0\u4e48\u6765\u5230\u7edd\u5bf9\u7537\u4eba\uff0c\u540c\u65f6\u8981\u4ece\u7b2c\u4e09\u4eba\u79f0\u89c6\u89d2\u6765\u5199\u7edd\u5bf9\u7537\u4eba\r\n\r\n\u300a\u7edd\u5bf9\u7537\u4eba\u4e3a\u4ec0\u4e48\u7a81\u7136\u706b\u8d77\u6765\u4e86\u300b\r\n\r\n\u548c\u5b9a\u4f4d\u6709\u5173\uff0c\u548c\u8ba4\u77e5\u7a81\u7834\u6709\u5173\uff0c\u4e5f\u548c\u6700\u91cd\u8981\u7684\u5173\u952e\u4eba\u7269\u52a0\u5165\u6709\u5173\uff0c\u4e00\u4f4d\u4e13\u95e8\u505a\u521b\u59cb\u4eba ip \u6253\u9020\u7684\u6444\u5f71\u5e08\u52a0\u5165\uff0c\u4f7f\u5f97\u7edd\u5bf9\u7537\u4eba\u5728\u4ece0\u52301\u4e0a\u7684\u901f\u5ea6\u5927\u5927\u63a8\u8fdb\uff0c\r\n\r\n\u300a\u7edd\u5bf9\u7537\u4eba IP \u6253\u9020\u5c11\u4e0d\u4e86\u4ed6\u300b\r\n\r\n\u8981\u52a0\u4e0a\u884c\u4e1a  \u73e0\u5b9d\u884c\u4e1a\u8001\u677f\u505a\u89c6\u9891\u53f7\u8981\u627e\u4ec0\u4e48\u6837\u7684\u5458\u5de5\r\n\r\n\r\n\u7edd\u5bf9\u7537\u4eba\uff0dIP \u5f71\u50cf\u64cd\u76d8\u624b\u6c34\u58a8\r\n\u65b0\u95fb\u8d26\u53f7\uff1a\r\n\r\n\u4eca\u65e5\u5934\u6761\r\n\u3002", "top": 0, "createdAt": 1731256356, "style": "", "script": "", "head": "", "ogImage": "https://github.githubassets.com/favicons/favicon.svg", "createdDate": "2024-11-11", "dateLabelColor": "#bc4c00"}, "P2": {"htmlDir": "docs/post/pu-tong-ren-bu-shi-he-zuo-xiao-lv-shu.html", "labels": ["documentation"], "postTitle": "\u666e\u901a\u4eba\u4e0d\u9002\u5408\u505a\u5c0f\u7eff\u4e66", "postUrl": "post/pu-tong-ren-bu-shi-he-zuo-xiao-lv-shu.html", "postSourceUrl": "https://github.com/hacksmo/hacksmo.github.io/issues/2", "commentNum": 0, "wordCount": 1064, "description": "\u5927\u5bb6\u597d  \u6211\u662f\u786c\u6838\u6c34\u58a8\uff0c\u8fd9\u4e24\u4e2a\u6708\u6d4b\u8bd5\u4e86\u51e0\u4e2a\u5708\u5b50\u91cc\u5f88\u706b\u7684\u641e\u94b1\u5c0f\u9879\u76ee\uff0c\u5c0f\u7ea2\u4e66\u865a\u62df\u8d44\u6599\u5f15\u6d41\uff0c\u5c0f\u5b66\u751f\u8d44\u6599\uff0c\u6559\u52a1\u8d44\u6599\uff0c\u5c0f\u7eff\u4e66\u56fe\u6587\u5e26\u8d27\u548c\u6d41\u91cf\u4e3b\u7b49\u7b49\u3002", "top": 0, "createdAt": 1731383483, "style": "", "script": "", "head": "", "ogImage": "https://github.githubassets.com/favicons/favicon.svg", "createdDate": "2024-11-12", "dateLabelColor": "#bc4c00"}}, "singeListJson": {}, "labelColorDict": {"bug": "#d73a4a", "documentation": "#0075ca", "duplicate": "#cfd3d7", "enhancement": "#a2eeef", "good first issue": "#7057ff", "help wanted": "#008672", "invalid": "#e4e669", "question": "#d876e3", "wontfix": "#ffffff"}, "displayTitle": "\u786c\u6838\u6c34\u58a8", "faviconUrl": "https://github.githubassets.com/favicons/favicon.svg", "ogImage": "https://github.githubassets.com/favicons/favicon.svg", "primerCSS": "<link href='https://mirrors.sustech.edu.cn/cdnjs/ajax/libs/Primer/21.0.7/primer.css' rel='stylesheet' />", "homeUrl": "https://hacksmo.github.io", "prevUrl": "disabled", "nextUrl": "disabled"}